nanofinderparser/__init__.py
nanofinderparser/cli.py
nanofinderparser/load.py
nanofinderparser/map.py
nanofinderparser/models.py
nanofinderparser/palettes.py
nanofinderparser/parsers.py
nanofinderparser/py.typed
nanofinderparser/units.py
nanofinderparser/utils.py
nanofinderparser-0.4.1.dist-info/METADATA
nanofinderparser-0.4.1.dist-info/WHEEL
nanofinderparser-0.4.1.dist-info/entry_points.txt
nanofinderparser-0.4.1.dist-info/licenses/AUTHORS.md
nanofinderparser-0.4.1.dist-info/licenses/LICENSE
nanofinderparser-0.4.1.dist-info/RECORD
