Metadata-Version: 2.4
Name: nanofinderparser
Version: 0.4.1
Summary: Parse and process Raman and photoluminescence (PL) data files generated by Nanofinder instruments.
Project-URL: Homepage, https://github.com/psolsfer/nanofinderparser
Project-URL: Repository, https://github.com/psolsfer/nanofinderparser
Project-URL: Documentation, https://nanofinderparser.readthedocs.io
Author-email: Pablo Solís-Fernández <psolsfer@gmail.com>
License-Expression: BSD-3-Clause
License-File: AUTHORS.md
License-File: LICENSE
Keywords: nanofinderparser
Classifier: Development Status :: 2 - Pre-Alpha
Classifier: Intended Audience :: Developers
Classifier: License :: OSI Approved :: BSD License
Classifier: Natural Language :: English
Classifier: Programming Language :: Python :: 3
Classifier: Programming Language :: Python :: 3.11
Classifier: Programming Language :: Python :: 3.12
Classifier: Programming Language :: Python :: 3.13
Requires-Python: <3.14,>=3.12
Requires-Dist: numpy>=2.1
Requires-Dist: pandas>=2.1
Requires-Dist: pint>=0.24.4
Requires-Dist: pydantic>=2.4.0
Requires-Dist: typer>=0.12
Requires-Dist: xmltodict>=0.10
